MotionTrackerBeta/__init__.py
MotionTrackerBeta/classes/__init__.py
MotionTrackerBeta/classes/classes.py
MotionTrackerBeta/functions/__init__.py
MotionTrackerBeta/functions/differentiate.py
MotionTrackerBeta/functions/display.py
MotionTrackerBeta/functions/helper.py
MotionTrackerBeta/functions/transforms.py
MotionTrackerBeta/images/backward.svg
MotionTrackerBeta/images/down.svg
MotionTrackerBeta/images/dropdown.png
MotionTrackerBeta/images/dropdown.svg
MotionTrackerBeta/images/end.svg
MotionTrackerBeta/images/forward.svg
MotionTrackerBeta/images/left.svg
MotionTrackerBeta/images/loader.gif
MotionTrackerBeta/images/logo.ico
MotionTrackerBeta/images/logo.svg
MotionTrackerBeta/images/pause.svg
MotionTrackerBeta/images/play.svg
MotionTrackerBeta/images/right.svg
MotionTrackerBeta/images/start.svg
MotionTrackerBeta/images/stop.svg
MotionTrackerBeta/images/tick.png
MotionTrackerBeta/images/up.svg
MotionTrackerBeta/images/video.svg
MotionTrackerBeta/images/zoom-in.svg
MotionTrackerBeta/images/zoom-out.svg
MotionTrackerBeta/LICENSE.txt
MotionTrackerBeta/main.py
MotionTrackerBeta/style/export.qss
MotionTrackerBeta/style/filter-derivative.qss
MotionTrackerBeta/style/main.qss
MotionTrackerBeta/style/message.qss
MotionTrackerBeta/style/postprocess.qss
MotionTrackerBeta/style/progress.qss
MotionTrackerBeta/style/rotation.qss
MotionTrackerBeta/style/tracking.qss
MotionTrackerBeta/widgets/__init__.py
MotionTrackerBeta/widgets/dialogs.py
MotionTrackerBeta/widgets/export.py
MotionTrackerBeta/widgets/gui.py
MotionTrackerBeta/widgets/lists.py
MotionTrackerBeta/widgets/process.py
MotionTrackerBeta/widgets/trackers.py
MotionTrackerBeta/widgets/video.py
motiontrackerbeta-0.1.6.dist-info/entry_points.txt
motiontrackerbeta-0.1.6.dist-info/LICENSE
motiontrackerbeta-0.1.6.dist-info/WHEEL
motiontrackerbeta-0.1.6.dist-info/METADATA
motiontrackerbeta-0.1.6.dist-info/RECORD
