Metadata-Version: 2.1
Name: motiontrackerbeta
Version: 0.1.6
Summary: a GUI based, open-source motion tracking application
Home-page: https://github.com/flochkristof/motiontracker
License: GPL-3.0
Author: Kristof Floch
Author-email: kristof.floch@gmail.com
Maintainer: Kristof Floch
Maintainer-email: kristof.floch@gmail.com
Requires-Python: >=3.8,<4.0
Classifier: Development Status :: 4 - Beta
Classifier: Intended Audience :: Science/Research
Classifier: License :: OSI Approved :: GNU General Public License v3 (GPLv3)
Classifier: License :: OSI Approved :: GNU General Public License v3 or later (GPLv3+)
Classifier: Operating System :: MacOS
Classifier: Operating System :: Microsoft :: Windows :: Windows 10
Classifier: Operating System :: POSIX :: Linux
Classifier: Programming Language :: Python :: 3
Classifier: Programming Language :: Python :: 3.8
Classifier: Programming Language :: Python :: 3.9
Classifier: Programming Language :: Python :: 3.10
Classifier: Programming Language :: Python :: 3.11
Classifier: Programming Language :: Python :: 3.10
Classifier: Programming Language :: Python :: 3.8
Classifier: Topic :: Scientific/Engineering :: Image Processing
Requires-Dist: PyQt5 (>=5.15.2,<6.0.0)
Requires-Dist: cvxopt (>=1.3.0,<2.0.0)
Requires-Dist: cvxpy (>=1.2.0,<2.0.0)
Requires-Dist: matplotlib (>=3.5.1,<4.0.0)
Requires-Dist: numpy (>=1.22.3,<2.0.0)
Requires-Dist: opencv-contrib-python-headless (>=4.5.5.64,<5.0.0.0)
Requires-Dist: openpyxl (>=3.0.10,<4.0.0)
Requires-Dist: pandas (>=1.4.2,<2.0.0)
Requires-Dist: pynumdiff (>=0.1.2,<0.2.0)
Requires-Dist: scipy (>=1.9.2,<2.0.0)
Project-URL: Repository, https://github.com/flochkristof/motiontracker
